rust_inspector/__init__.py
rust_inspector/binary.py
rust_inspector/blint_binary.py
rust_inspector/blint_binary.py.ABOUT
rust_inspector/blint_binary.py.LICENSE
rust_inspector/config.py
rust_inspector/packages.py
rust_inspector/plugin.py
rust_inspector-0.1.0.dist-info/AUTHORS.rst
rust_inspector-0.1.0.dist-info/CHANGELOG.rst
rust_inspector-0.1.0.dist-info/CODE_OF_CONDUCT.rst
rust_inspector-0.1.0.dist-info/METADATA
rust_inspector-0.1.0.dist-info/NOTICE
rust_inspector-0.1.0.dist-info/WHEEL
rust_inspector-0.1.0.dist-info/apache-2.0.LICENSE
rust_inspector-0.1.0.dist-info/entry_points.txt
rust_inspector-0.1.0.dist-info/top_level.txt
rust_inspector-0.1.0.dist-info/RECORD
